omdata/__init__.py
omdata/__version__.py
omdata/design.py
omdata/validator.py
omdata-0.1.5.data/scripts/om-json
omdata-0.1.5.dist-info/DESCRIPTION.rst
omdata-0.1.5.dist-info/METADATA
omdata-0.1.5.dist-info/RECORD
omdata-0.1.5.dist-info/WHEEL
omdata-0.1.5.dist-info/entry_points.txt
omdata-0.1.5.dist-info/metadata.json
omdata-0.1.5.dist-info/top_level.txt
