Metadata-Version: 2.0
Name: omdata
Version: 0.1.5
Summary: A JSON schema editor and validator for OpenMaker survey data.
Home-page: http://github.com/bulentozel/omdata
Author: Bulent Ozel
Author-email: bulent.ozel@gmail.com
License: Apache2
Platform: UNKNOWN
Classifier: License :: OSI Approved :: Apache Software License
Classifier: Development Status :: 2 - Pre-Alpha
Classifier: Programming Language :: Python
Classifier: Programming Language :: Python :: 2.7
Classifier: Programming Language :: Python :: 3.6
Requires-Python: >=2.7.0
Requires-Dist: jsonschema
